{
  "annotations": {
    "list": [
      {
        "builtIn": 1,
        "datasource": {
          "type": "datasource",
          "uid": "grafana"
        },
        "enable": true,
        "hide": true,
        "iconColor": "rgba(0, 211, 255, 1)",
        "name": "Annotations & Alerts",
        "type": "dashboard"
      }
    ]
  },
  "editable": true,
  "fiscalYearStartMonth": 0,
  "graphTooltip": 1,
  "id": null,
  "links": [],
  "panels": [
    {
      "datasource": {
        "type": "prometheus",
        "uid": "DS_VICTORIAMETRICS"
      },
      "fieldConfig": {
        "defaults": {
          "color": {
            "mode": "palette-classic"
          },
          "custom": {
            "axisBorderShow": false,
            "axisCenteredZero": false,
            "axisColorMode": "text",
            "axisLabel": "",
            "axisPlacement": "auto",
            "barAlignment": 0,
            "barWidthFactor": 0.6,
            "drawStyle": "line",
            "fillOpacity": 20,
            "gradientMode": "opacity",
            "hideFrom": {
              "tooltip": false,
              "viz": false,
              "legend": false
            },
            "insertNulls": false,
            "lineInterpolation": "smooth",
            "lineWidth": 2,
            "pointSize": 5,
            "scaleDistribution": {
              "type": "linear"
            },
            "showPoints": "never",
            "spanNulls": false,
            "stacking": {
              "group": "A",
              "mode": "none"
            },
            "thresholdsStyle": {
              "mode": "off"
            }
          },
          "mappings": [],
          "thresholds": {
            "mode": "absolute",
            "steps": [
              {
                "color": "green",
                "value": null
              },
              {
                "color": "yellow",
                "value": 20
              },
              {
                "color": "red",
                "value": 30
              }
            ]
          },
          "unit": "fps"
        },
        "overrides": []
      },
      "gridPos": {
        "h": 8,
        "w": 12,
        "x": 0,
        "y": 0
      },
      "id": 1,
      "options": {
        "legend": {
          "calcs": ["mean", "last", "max"],
          "displayMode": "table",
          "placement": "bottom",
          "showLegend": true
        },
        "tooltip": {
          "mode": "multi",
          "sort": "desc"
        }
      },
      "pluginVersion": "11.0.0",
      "targets": [
        {
          "datasource": {
            "type": "prometheus",
            "uid": "DS_VICTORIAMETRICS"
          },
          "expr": "ffmpeg_fps",
          "legendFormat": "FPS",
          "refId": "A"
        }
      ],
      "title": "FFmpeg Encoding FPS",
      "type": "timeseries"
    },
    {
      "datasource": {
        "type": "prometheus",
        "uid": "DS_VICTORIAMETRICS"
      },
      "fieldConfig": {
        "defaults": {
          "color": {
            "mode": "palette-classic"
          },
          "custom": {
            "axisBorderShow": false,
            "axisCenteredZero": false,
            "axisColorMode": "text",
            "axisLabel": "",
            "axisPlacement": "auto",
            "barAlignment": 0,
            "barWidthFactor": 0.6,
            "drawStyle": "line",
            "fillOpacity": 20,
            "gradientMode": "opacity",
            "hideFrom": {
              "tooltip": false,
              "viz": false,
              "legend": false
            },
            "insertNulls": false,
            "lineInterpolation": "smooth",
            "lineWidth": 2,
            "pointSize": 5,
            "scaleDistribution": {
              "type": "linear"
            },
            "showPoints": "never",
            "spanNulls": false,
            "stacking": {
              "group": "A",
              "mode": "none"
            },
            "thresholdsStyle": {
              "mode": "off"
            }
          },
          "mappings": [],
          "thresholds": {
            "mode": "absolute",
            "steps": [
              {
                "color": "green",
                "value": null
              }
            ]
          },
          "unit": "Kbits"
        },
        "overrides": [
          {
            "matcher": {
              "id": "byName",
              "options": "Current Bitrate"
            },
            "properties": [
              {
                "id": "color",
                "value": {
                  "fixedColor": "blue",
                  "mode": "fixed"
                }
              }
            ]
          },
          {
            "matcher": {
              "id": "byName",
              "options": "Average Bitrate"
            },
            "properties": [
              {
                "id": "color",
                "value": {
                  "fixedColor": "green",
                  "mode": "fixed"
                }
              },
              {
                "id": "custom.lineStyle",
                "value": {
                  "dash": [10, 10],
                  "fill": "dash"
                }
              }
            ]
          }
        ]
      },
      "gridPos": {
        "h": 8,
        "w": 12,
        "x": 12,
        "y": 0
      },
      "id": 2,
      "options": {
        "legend": {
          "calcs": ["mean", "last", "max"],
          "displayMode": "table",
          "placement": "bottom",
          "showLegend": true
        },
        "tooltip": {
          "mode": "multi",
          "sort": "desc"
        }
      },
      "pluginVersion": "11.0.0",
      "targets": [
        {
          "datasource": {
            "type": "prometheus",
            "uid": "DS_VICTORIAMETRICS"
          },
          "expr": "ffmpeg_current_bitrate_kbps",
          "legendFormat": "Current Bitrate",
          "refId": "A"
        },
        {
          "datasource": {
            "type": "prometheus",
            "uid": "DS_VICTORIAMETRICS"
          },
          "expr": "ffmpeg_avg_bitrate_kbps",
          "legendFormat": "Average Bitrate",
          "refId": "B"
        }
      ],
      "title": "FFmpeg Output Bitrate",
      "type": "timeseries"
    },
    {
      "datasource": {
        "type": "prometheus",
        "uid": "DS_VICTORIAMETRICS"
      },
      "fieldConfig": {
        "defaults": {
          "color": {
            "mode": "thresholds"
          },
          "mappings": [],
          "thresholds": {
            "mode": "absolute",
            "steps": [
              {
                "color": "green",
                "value": null
              },
              {
                "color": "yellow",
                "value": 0.8
              },
              {
                "color": "orange",
                "value": 1.2
              },
              {
                "color": "red",
                "value": 2
              }
            ]
          },
          "unit": "none"
        },
        "overrides": []
      },
      "gridPos": {
        "h": 6,
        "w": 6,
        "x": 0,
        "y": 8
      },
      "id": 3,
      "options": {
        "minVizHeight": 75,
        "minVizWidth": 75,
        "orientation": "auto",
        "reduceOptions": {
          "values": false,
          "calcs": ["lastNotNull"],
          "fields": ""
        },
        "showThresholdLabels": false,
        "showThresholdMarkers": true,
        "sizing": "auto",
        "text": {
          "valueSize": 48
        }
      },
      "pluginVersion": "11.0.0",
      "targets": [
        {
          "datasource": {
            "type": "prometheus",
            "uid": "DS_VICTORIAMETRICS"
          },
          "expr": "ffmpeg_speed",
          "refId": "A"
        }
      ],
      "title": "Encoding Speed (1.0 = Realtime)",
      "type": "gauge"
    },
    {
      "datasource": {
        "type": "prometheus",
        "uid": "DS_VICTORIAMETRICS"
      },
      "fieldConfig": {
        "defaults": {
          "color": {
            "mode": "thresholds"
          },
          "mappings": [],
          "thresholds": {
            "mode": "absolute",
            "steps": [
              {
                "color": "green",
                "value": null
              },
              {
                "color": "yellow",
                "value": 10
              },
              {
                "color": "red",
                "value": 50
              }
            ]
          },
          "unit": "short"
        },
        "overrides": []
      },
      "gridPos": {
        "h": 6,
        "w": 6,
        "x": 6,
        "y": 8
      },
      "id": 4,
      "options": {
        "colorMode": "value",
        "graphMode": "area",
        "justifyMode": "auto",
        "orientation": "auto",
        "reduceOptions": {
          "values": false,
          "calcs": ["lastNotNull"],
          "fields": ""
        },
        "showPercentChange": false,
        "textMode": "auto",
        "wideLayout": true
      },
      "pluginVersion": "11.0.0",
      "targets": [
        {
          "datasource": {
            "type": "prometheus",
            "uid": "DS_VICTORIAMETRICS"
          },
          "expr": "ffmpeg_dropped_frames_total",
          "refId": "A"
        }
      ],
      "title": "Dropped Frames",
      "type": "stat"
    },
    {
      "datasource": {
        "type": "prometheus",
        "uid": "DS_VICTORIAMETRICS"
      },
      "fieldConfig": {
        "defaults": {
          "color": {
            "mode": "thresholds"
          },
          "mappings": [],
          "thresholds": {
            "mode": "absolute",
            "steps": [
              {
                "color": "green",
                "value": null
              }
            ]
          },
          "unit": "short"
        },
        "overrides": []
      },
      "gridPos": {
        "h": 6,
        "w": 6,
        "x": 12,
        "y": 8
      },
      "id": 5,
      "options": {
        "colorMode": "value",
        "graphMode": "area",
        "justifyMode": "auto",
        "orientation": "auto",
        "reduceOptions": {
          "values": false,
          "calcs": ["lastNotNull"],
          "fields": ""
        },
        "showPercentChange": false,
        "textMode": "auto",
        "wideLayout": true
      },
      "pluginVersion": "11.0.0",
      "targets": [
        {
          "datasource": {
            "type": "prometheus",
            "uid": "DS_VICTORIAMETRICS"
          },
          "expr": "ffmpeg_frames_total",
          "refId": "A"
        }
      ],
      "title": "Total Frames Processed",
      "type": "stat"
    },
    {
      "datasource": {
        "type": "prometheus",
        "uid": "DS_VICTORIAMETRICS"
      },
      "fieldConfig": {
        "defaults": {
          "color": {
            "mode": "thresholds"
          },
          "mappings": [],
          "max": 100,
          "min": 0,
          "thresholds": {
            "mode": "absolute",
            "steps": [
              {
                "color": "green",
                "value": null
              },
              {
                "color": "yellow",
                "value": 70
              },
              {
                "color": "red",
                "value": 90
              }
            ]
          },
          "unit": "percent"
        },
        "overrides": []
      },
      "gridPos": {
        "h": 6,
        "w": 6,
        "x": 18,
        "y": 8
      },
      "id": 6,
      "options": {
        "minVizHeight": 75,
        "minVizWidth": 75,
        "orientation": "auto",
        "reduceOptions": {
          "values": false,
          "calcs": ["lastNotNull"],
          "fields": ""
        },
        "showThresholdLabels": false,
        "showThresholdMarkers": true,
        "sizing": "auto"
      },
      "pluginVersion": "11.0.0",
      "targets": [
        {
          "datasource": {
            "type": "prometheus",
            "uid": "DS_VICTORIAMETRICS"
          },
          "expr": "ffmpeg_encoder_load_percent",
          "refId": "A"
        }
      ],
      "title": "Encoder Load",
      "type": "gauge"
    },
    {
      "datasource": {
        "type": "prometheus",
        "uid": "DS_VICTORIAMETRICS"
      },
      "fieldConfig": {
        "defaults": {
          "color": {
            "mode": "palette-classic"
          },
          "custom": {
            "axisBorderShow": false,
            "axisCenteredZero": false,
            "axisColorMode": "text",
            "axisLabel": "",
            "axisPlacement": "auto",
            "barAlignment": 0,
            "barWidthFactor": 0.6,
            "drawStyle": "line",
            "fillOpacity": 10,
            "gradientMode": "none",
            "hideFrom": {
              "tooltip": false,
              "viz": false,
              "legend": false
            },
            "insertNulls": false,
            "lineInterpolation": "linear",
            "lineWidth": 1,
            "pointSize": 5,
            "scaleDistribution": {
              "type": "linear"
            },
            "showPoints": "never",
            "spanNulls": false,
            "stacking": {
              "group": "A",
              "mode": "none"
            },
            "thresholdsStyle": {
              "mode": "off"
            }
          },
          "mappings": [],
          "thresholds": {
            "mode": "absolute",
            "steps": [
              {
                "color": "green",
                "value": null
              }
            ]
          },
          "unit": "ms"
        },
        "overrides": []
      },
      "gridPos": {
        "h": 8,
        "w": 12,
        "x": 0,
        "y": 14
      },
      "id": 7,
      "options": {
        "legend": {
          "calcs": ["mean", "max"],
          "displayMode": "table",
          "placement": "bottom",
          "showLegend": true
        },
        "tooltip": {
          "mode": "multi",
          "sort": "desc"
        }
      },
      "pluginVersion": "11.0.0",
      "targets": [
        {
          "datasource": {
            "type": "prometheus",
            "uid": "DS_VICTORIAMETRICS"
          },
          "expr": "ffmpeg_encode_latency_ms",
          "legendFormat": "Encode Latency",
          "refId": "A"
        }
      ],
      "title": "FFmpeg Encode Latency",
      "type": "timeseries"
    },
    {
      "datasource": {
        "type": "prometheus",
        "uid": "DS_VICTORIAMETRICS"
      },
      "fieldConfig": {
        "defaults": {
          "color": {
            "mode": "palette-classic"
          },
          "custom": {
            "axisBorderShow": false,
            "axisCenteredZero": false,
            "axisColorMode": "text",
            "axisLabel": "",
            "axisPlacement": "auto",
            "barAlignment": 0,
            "barWidthFactor": 0.6,
            "drawStyle": "line",
            "fillOpacity": 10,
            "gradientMode": "none",
            "hideFrom": {
              "tooltip": false,
              "viz": false,
              "legend": false
            },
            "insertNulls": false,
            "lineInterpolation": "linear",
            "lineWidth": 1,
            "pointSize": 5,
            "scaleDistribution": {
              "type": "linear"
            },
            "showPoints": "never",
            "spanNulls": false,
            "stacking": {
              "group": "A",
              "mode": "none"
            },
            "thresholdsStyle": {
              "mode": "off"
            }
          },
          "mappings": [],
          "thresholds": {
            "mode": "absolute",
            "steps": [
              {
                "color": "green",
                "value": null
              }
            ]
          },
          "unit": "short"
        },
        "overrides": []
      },
      "gridPos": {
        "h": 8,
        "w": 12,
        "x": 12,
        "y": 14
      },
      "id": 8,
      "options": {
        "legend": {
          "calcs": ["mean", "last"],
          "displayMode": "table",
          "placement": "bottom",
          "showLegend": true
        },
        "tooltip": {
          "mode": "multi",
          "sort": "desc"
        }
      },
      "pluginVersion": "11.0.0",
      "targets": [
        {
          "datasource": {
            "type": "prometheus",
            "uid": "DS_VICTORIAMETRICS"
          },
          "expr": "nginx_rtmp_streams",
          "legendFormat": "Active Streams",
          "refId": "A"
        },
        {
          "datasource": {
            "type": "prometheus",
            "uid": "DS_VICTORIAMETRICS"
          },
          "expr": "nginx_rtmp_viewers_total",
          "legendFormat": "Total Viewers",
          "refId": "B"
        }
      ],
      "title": "RTMP Server Stats",
      "type": "timeseries"
    },
    {
      "datasource": {
        "type": "prometheus",
        "uid": "DS_VICTORIAMETRICS"
      },
      "fieldConfig": {
        "defaults": {
          "color": {
            "mode": "palette-classic"
          },
          "custom": {
            "axisBorderShow": false,
            "axisCenteredZero": false,
            "axisColorMode": "text",
            "axisLabel": "",
            "axisPlacement": "auto",
            "barAlignment": 0,
            "barWidthFactor": 0.6,
            "drawStyle": "line",
            "fillOpacity": 20,
            "gradientMode": "opacity",
            "hideFrom": {
              "tooltip": false,
              "viz": false,
              "legend": false
            },
            "insertNulls": false,
            "lineInterpolation": "smooth",
            "lineWidth": 2,
            "pointSize": 5,
            "scaleDistribution": {
              "type": "linear"
            },
            "showPoints": "never",
            "spanNulls": false,
            "stacking": {
              "group": "A",
              "mode": "none"
            },
            "thresholdsStyle": {
              "mode": "off"
            }
          },
          "mappings": [],
          "thresholds": {
            "mode": "absolute",
            "steps": [
              {
                "color": "green",
                "value": null
              }
            ]
          },
          "unit": "none"
        },
        "overrides": []
      },
      "gridPos": {
        "h": 8,
        "w": 24,
        "x": 0,
        "y": 22
      },
      "id": 9,
      "options": {
        "legend": {
          "calcs": ["mean", "last"],
          "displayMode": "table",
          "placement": "right",
          "showLegend": true
        },
        "tooltip": {
          "mode": "multi",
          "sort": "desc"
        }
      },
      "pluginVersion": "11.0.0",
      "targets": [
        {
          "datasource": {
            "type": "prometheus",
            "uid": "DS_VICTORIAMETRICS"
          },
          "expr": "rate(ffmpeg_frames_total[1m]) * 60",
          "legendFormat": "Frames per Minute",
          "refId": "A"
        },
        {
          "datasource": {
            "type": "prometheus",
            "uid": "DS_VICTORIAMETRICS"
          },
          "expr": "rate(ffmpeg_dropped_frames_total[1m]) * 60",
          "legendFormat": "Dropped Frames per Minute",
          "refId": "B"
        }
      ],
      "title": "Frame Processing Rate",
      "type": "timeseries"
    }
  ],
  "refresh": "5s",
  "schemaVersion": 39,
  "tags": ["transcoding", "ffmpeg", "performance"],
  "templating": {
    "list": []
  },
  "time": {
    "from": "now-15m",
    "to": "now"
  },
  "timepicker": {},
  "timezone": "browser",
  "title": "Transcoding Performance",
  "uid": "transcoding-performance",
  "version": 1,
  "weekStart": ""
}
